progress_api/__init__.py
progress_api/api.py
progress_api/config.py
progress_api/py.typed
progress_api/util.py
progress_api/backends/__init__.py
progress_api/backends/enlighten.py
progress_api/backends/mock.py
progress_api/backends/null.py
progress_api/backends/tqdm.py
progress_api-0.1.0.dist-info/LICENSE.md
progress_api-0.1.0.dist-info/METADATA
progress_api-0.1.0.dist-info/WHEEL
progress_api-0.1.0.dist-info/entry_points.txt
progress_api-0.1.0.dist-info/top_level.txt
progress_api-0.1.0.dist-info/RECORD
