Metadata-Version: 2.1
Name: progress-api
Version: 0.1.0
Summary: Backend-agnostic API for reporting progress.
Author-email: Michael Ekstrand <mdekstrand@drexel.edu>
License: Copyright (c) 2023 Drexel University and contributors
Project-URL: Homepage, https://progress-api.lenksit.org
Project-URL: GitHub, https://github.com/lenskit/progress-api
Classifier: License :: OSI Approved :: MIT License
Classifier: Programming Language :: Python :: 3
Classifier: Programming Language :: Python :: 3.10
Classifier: Programming Language :: Python :: 3.11
Classifier: Programming Language :: Python :: 3.12
Classifier: Operating System :: OS Independent
Requires-Python: >=3.10
License-File: LICENSE.md
Provides-Extra: dev
Requires-Dist: setuptools >=64 ; extra == 'dev'
Requires-Dist: setuptools-scm >=8 ; extra == 'dev'
Requires-Dist: build ==1.* ; extra == 'dev'
Requires-Dist: ruff >=0.2 ; extra == 'dev'
Requires-Dist: pyright ; extra == 'dev'
Requires-Dist: copier ==9.* ; extra == 'dev'
Requires-Dist: unbeheader ~=1.3 ; extra == 'dev'
Requires-Dist: ipython ; extra == 'dev'
Requires-Dist: pyproject2conda ; extra == 'dev'
Requires-Dist: sphinx-autobuild ; extra == 'dev'
Requires-Dist: enlighten ==1.* ; extra == 'dev'
Requires-Dist: tqdm ==4.* ; extra == 'dev'
Provides-Extra: doc
Requires-Dist: sphinx >=4.2 ; extra == 'doc'
Requires-Dist: sphinxext-opengraph >=0.5 ; extra == 'doc'
Requires-Dist: furo ; extra == 'doc'
Requires-Dist: enlighten ; extra == 'doc'
Requires-Dist: tqdm ; extra == 'doc'
Provides-Extra: test
Requires-Dist: pytest >=7 ; extra == 'test'
